murl.py
murl-0.5.1.dist-info/metadata.json
murl-0.5.1.dist-info/METADATA
murl-0.5.1.dist-info/DESCRIPTION.rst
murl-0.5.1.dist-info/WHEEL
murl-0.5.1.dist-info/RECORD
murl-0.5.1.dist-info/top_level.txt
