Metadata-Version: 2.0
Name: murl
Version: 0.5.1
Summary: murl is a tiny wrapper for the Python module urlparse.
Home-page: https://github.com/berkerpeksag/murl
Author: Berker Peksag
Author-email: berker.peksag@gmail.com
License: Mozilla Public License, v. 2.0
Platform: any
Classifier: Development Status :: 5 - Production/Stable
Classifier: Topic :: Internet :: WWW/HTTP
Classifier: Programming Language :: Python
Classifier: Programming Language :: Python :: 2
Classifier: Programming Language :: Python :: 2.6
Classifier: Programming Language :: Python :: 2.7
Classifier: Programming Language :: Python :: 3
Classifier: Programming Language :: Python :: 3.2
Classifier: Programming Language :: Python :: 3.3
Classifier: Programming Language :: Python :: 3.4
Classifier: License :: OSI Approved :: Mozilla Public License 2.0 (MPL 2.0)
